juliaup/__init__.py
juliaup-0.1.1.dist-info/LICENSE
juliaup-0.1.1.dist-info/METADATA
juliaup-0.1.1.dist-info/WHEEL
juliaup-0.1.1.dist-info/top_level.txt
juliaup-0.1.1.dist-info/RECORD
