Metadata-Version: 2.1
Name: juliaup
Version: 0.1.1
Summary: An interface to the
License: MIT
Project-URL: Home, http://github.com/cjdoris/pyjuliaup
Platform: UNKNOWN
Classifier: Framework :: Django
Classifier: License :: OSI Approved :: MIT License
Classifier: Programming Language :: Python :: 3
License-File: LICENSE
